cache_toolbox/__init__.py
cache_toolbox/app_settings.py
cache_toolbox/core.py
cache_toolbox/middleware.py
cache_toolbox/model.py
cache_toolbox/relation.py
cache_toolbox/templatetags/__init__.py
cache_toolbox/templatetags/cache_toolbox.py
django_cache_toolbox-1.6.1.dist-info/COPYING
django_cache_toolbox-1.6.1.dist-info/METADATA
django_cache_toolbox-1.6.1.dist-info/WHEEL
django_cache_toolbox-1.6.1.dist-info/top_level.txt
django_cache_toolbox-1.6.1.dist-info/RECORD
