Metadata-Version: 2.1
Name: django-cache-toolbox
Version: 1.6.1
Summary: Non-magical object caching for Django.
Home-page: https://chris-lamb.co.uk/projects/django-cache-toolbox
Author: Chris Lamb
Author-email: chris@chris-lamb.co.uk
License: BSD
Platform: UNKNOWN
License-File: COPYING
Requires-Dist: Django (>=1.9)
